cubeblock/__init__.py
cubeblock/functions.py
cubeblock-0.0.2.dist-info/METADATA
cubeblock-0.0.2.dist-info/WHEEL
cubeblock-0.0.2.dist-info/top_level.txt
cubeblock-0.0.2.dist-info/RECORD
