Metadata-Version: 2.1
Name: cubeblock
Version: 0.0.2
Summary: Cube official python library
Home-page: https://www.getcube.ai
Author: Sacha Ichbiah
Author-email: sacha.ichbiah@gmail.com
Project-URL: Team website, https://www.getcube.ai
Classifier: Programming Language :: Python :: 3
Classifier: License :: OSI Approved :: MIT License
Classifier: Operating System :: POSIX :: Linux
Classifier: Operating System :: MacOS
Classifier: License :: OSI Approved :: MIT License
Classifier: Intended Audience :: Science/Research
Requires-Dist: numpy >=1.21.6
Requires-Dist: matplotlib >=3.3.1
